setup.py
rockpaperscissor/__init__.py
rockpaperscissor.egg-info/PKG-INFO
rockpaperscissor.egg-info/SOURCES.txt
rockpaperscissor.egg-info/dependency_links.txt
rockpaperscissor.egg-info/requires.txt
rockpaperscissor.egg-info/top_level.txt