Metadata-Version: 1.0
Name: rockpaperscissor
Version: 0.1
Summary: Rock Paper Scissor
Home-page: https://pypi.python.org/pypi
Author: Mridu Bhattacharya
Author-email: mridubhattacharya@live.com
License: UNKNOWN
Platform: UNKNOWN
